SafeTransformer/SafeTransformer.py
SafeTransformer/__init__.py
safe_transformer_fixed-0.2.0.dist-info/LICENSE
safe_transformer_fixed-0.2.0.dist-info/METADATA
safe_transformer_fixed-0.2.0.dist-info/WHEEL
safe_transformer_fixed-0.2.0.dist-info/top_level.txt
safe_transformer_fixed-0.2.0.dist-info/RECORD
