Metadata-Version: 2.1
Name: safe-transformer-fixed
Version: 0.2.0
Summary: Build explainable ML models using surrogate models.
Home-page: https://github.com/olagacek/SAFE
Author: Aleksandra Gacek, Piotr Luboń
Author-email: lubonp@student.mini.pw.edu.pl, gaceka@student.mini.pw.edu.pl
Maintainer: Dilshan Sonnadara
Maintainer-email: dilshan.sonnadara13@gmail.com
Classifier: Programming Language :: Python :: 3
Classifier: License :: OSI Approved :: MIT License
Classifier: Operating System :: OS Independent
License-File: LICENSE
Requires-Dist: numpy
Requires-Dist: ruptures
Requires-Dist: scikit-learn
Requires-Dist: pandas
Requires-Dist: scipy
Requires-Dist: kneed
